setup.py
Nitin_distributions/Binomialdistribution.py
Nitin_distributions/Gaussiandistribution.py
Nitin_distributions/Generaldistribution.py
Nitin_distributions/__init__.py
Nitin_distributions.egg-info/PKG-INFO
Nitin_distributions.egg-info/SOURCES.txt
Nitin_distributions.egg-info/dependency_links.txt
Nitin_distributions.egg-info/not-zip-safe
Nitin_distributions.egg-info/top_level.txt